mask_util/__init__.py
mask_util/const.py
mask_util/mask.py
mask_util/replacer.py
mask_util-0.1.0.dist-info/METADATA
mask_util-0.1.0.dist-info/WHEEL
mask_util-0.1.0.dist-info/top_level.txt
mask_util-0.1.0.dist-info/RECORD
